knita/__init__.py
knita/client.py
knita/director_pb2.py
knita/director_pb2.pyi
knita/director_pb2_grpc.py
knita/executor_pb2.py
knita/executor_pb2.pyi
knita/executor_pb2_grpc.py
knita/runtime.py
knita-0.0.3.dist-info/METADATA
knita-0.0.3.dist-info/WHEEL
knita-0.0.3.dist-info/licenses/LICENSE
knita-0.0.3.dist-info/RECORD
